st_top_menu/__init__.py
st_top_menu/frontend/build/asset-manifest.json
st_top_menu/frontend/build/bootstrap.min.css
st_top_menu/frontend/build/index.html
st_top_menu/frontend/build/precache-manifest.7c4a56cb5c258007f177780ba3850609.js
st_top_menu/frontend/build/service-worker.js
st_top_menu/frontend/build/static/css/main.6c47e604.chunk.css
st_top_menu/frontend/build/static/css/main.6c47e604.chunk.css.map
st_top_menu/frontend/build/static/js/2.a516ac97.chunk.js
st_top_menu/frontend/build/static/js/2.a516ac97.chunk.js.LICENSE.txt
st_top_menu/frontend/build/static/js/2.a516ac97.chunk.js.map
st_top_menu/frontend/build/static/js/main.45659150.chunk.js
st_top_menu/frontend/build/static/js/main.45659150.chunk.js.map
st_top_menu/frontend/build/static/js/runtime-main.11ec9aca.js
st_top_menu/frontend/build/static/js/runtime-main.11ec9aca.js.map
streamlit_top_menu-0.0.3.dist-info/LICENSE
streamlit_top_menu-0.0.3.dist-info/METADATA
streamlit_top_menu-0.0.3.dist-info/WHEEL
streamlit_top_menu-0.0.3.dist-info/top_level.txt
streamlit_top_menu-0.0.3.dist-info/RECORD
